odoo/addons/auth_ldaps/README.rst
odoo/addons/auth_ldaps/__init__.py
odoo/addons/auth_ldaps/__manifest__.py
odoo/addons/auth_ldaps/models/__init__.py
odoo/addons/auth_ldaps/models/res_company_ldap.py
odoo/addons/auth_ldaps/static/description/icon.png
odoo/addons/auth_ldaps/views/res_company_ldap_views.xml
odoo11_addon_auth_ldaps-11.0.1.0.0.dist-info/DESCRIPTION.rst
odoo11_addon_auth_ldaps-11.0.1.0.0.dist-info/METADATA
odoo11_addon_auth_ldaps-11.0.1.0.0.dist-info/RECORD
odoo11_addon_auth_ldaps-11.0.1.0.0.dist-info/WHEEL
odoo11_addon_auth_ldaps-11.0.1.0.0.dist-info/metadata.json
odoo11_addon_auth_ldaps-11.0.1.0.0.dist-info/top_level.txt
